{
  "success": true,
  "count": 12,
  "data": [
    {
      "date": "09.11.2025 17:08:43",
      "name": "Федорчук Алексей Витальевич",
      "phone": "79371471560",
      "age": "38",
      "conferenceDay": "28-29 ноября (оба дня)",
      "accommodation": "Нет",
      "payment": "Оплата наличными на месте",
      "telegram": "Alekseu87",
      "notes": ""
    },
    {
      "date": "09.11.2025 17:05:23",
      "name": "Самарин Евгений Николаевич",
      "phone": "79044054138",
      "age": "17",
      "conferenceDay": "28-29 ноября (оба дня)",
      "accommodation": "Да",
      "payment": "Оплата наличными на месте",
      "telegram": "zhenyasamarin",
      "notes": ""
    },
    {
      "date": "09.11.2025 16:21:38",
      "name": "Захарченко Марк Сергеевич",
      "phone": "79093775330",
      "age": "19",
      "conferenceDay": "28-29 ноября (оба дня)",
      "accommodation": "Да",
      "payment": "Оплата по карте",
      "telegram": "Markus_zaha",
      "notes": ""
    },
    {
      "date": "09.11.2025 15:40:26",
      "name": "Селиверстова Виктория Александровна",
      "phone": "79539775717",
      "age": "22",
      "conferenceDay": "28-29 ноября (оба дня)",
      "accommodation": "Нет",
      "payment": "Оплата наличными на месте",
      "telegram": "Vikasmotrit",
      "notes": ""
    },
    {
      "date": "09.11.2025 14:23:03",
      "name": "Пугачев Андрей",
      "phone": "79378180979",
      "age": "50",
      "conferenceDay": "28 ноября",
      "accommodation": "Нет",
      "payment": "Оплата наличными на месте",
      "telegram": "pugachevphoto",
      "notes": ""
    },
    {
      "date": "09.11.2025 10:02:34",
      "name": "Ковалева Татьяна Павловна",
      "phone": "79658840152",
      "age": "24",
      "conferenceDay": "28-29 ноября (оба дня)",
      "accommodation": "Нет",
      "payment": "Оплата наличными на месте",
      "telegram": "@mercyme0",
      "notes": ""
    },
    {
      "date": "09.11.2025 08:35:18",
      "name": "Сучков Павел Михайлович",
      "phone": "79649986642",
      "age": "19",
      "conferenceDay": "28-29 ноября (оба дня)",
      "accommodation": "Да",
      "payment": "Оплата наличными на месте",
      "telegram": "Pashtet_SuchkoV",
      "notes": ""
    },
    {
      "date": "09.11.2025 06:40:20",
      "name": "Аргентовский Сергей Михайлович",
      "phone": "79889359785",
      "age": "21",
      "conferenceDay": "28-29 ноября (оба дня)",
      "accommodation": "Нет",
      "payment": "Оплата по карте",
      "telegram": "Serj07Sa",
      "notes": ""
    },
    {
      "date": "09.11.2025 05:37:43",
      "name": "Аргентовский Михаил Михайлович",
      "phone": "89889346820",
      "age": "23",
      "conferenceDay": "28-29 ноября (оба дня)",
      "accommodation": "Нет",
      "payment": "Оплата наличными на месте",
      "telegram": "@vogidfos",
      "notes": ""
    },
    {
      "date": "09.11.2025 05:35:05",
      "name": "Бовт Илия Сергеевич",
      "phone": "79878124864",
      "age": "24",
      "conferenceDay": "28-29 ноября (оба дня)",
      "accommodation": "Нет",
      "payment": "Оплата наличными на месте",
      "telegram": "Iliya_Bovt",
      "notes": ""
    },
    {
      "date": "09.11.2025 05:33:46",
      "name": "Гематова Асия Руслановна",
      "phone": "+79998072802",
      "age": "18",
      "conferenceDay": "28-29 ноября (оба дня)",
      "accommodation": "Нет",
      "payment": "Оплата наличными на месте",
      "telegram": "blessed_heart1",
      "notes": ""
    },
    {
      "date": "08.11.2025 22:50:35",
      "name": "Аргентовский Вениамин Михаилович",
      "phone": "+79889213228",
      "age": "19",
      "conferenceDay": "28-29 ноября (оба дня)",
      "accommodation": "Нет",
      "payment": "Оплата наличными на месте",
      "telegram": "BenjARG",
      "notes": ""
    }
  ],
  "stats": {
    "under18": 1,
    "day28": 1,
    "day29": 0,
    "both": 11,
    "accommodation": 3,
    "remainingTime": {
      "closed": false,
      "message": "10 дн. 6 ч. 51 мин."
    },
    "endDate": "2025-11-20T00:00:00.000Z",
    "lastUpdate": "2025-11-09T17:08:43.802Z"
  }
}